polyprops-1.0.2.dist-info/METADATA
polyprops-1.0.2.dist-info/WHEEL
polyprops-1.0.2.dist-info/license_files/LICENSE.txt
polyprops/__init__.py
polyprops/polyprops.cp312-win_amd64.pyd
polyprops-1.0.2.dist-info/RECORD
