Metadata-Version: 2.1
Name: polyprops
Version: 1.0.2
Classifier: Programming Language :: Rust
Classifier: Programming Language :: Python :: Implementation :: CPython
Classifier: Programming Language :: Python :: Implementation :: PyPy
License-File: LICENSE.txt
Summary: A Python package used for the analysis of polygon properties with a focus on performance.
Author: Kyle Lessa
Requires-Python: >=3.10
Project-URL: homepage, https://github.com/k-lessa/polyprops
